pyescrypt-0.1.0.data/purelib/.DS_Store
pyescrypt-0.1.0.data/purelib/pyescrypt/__init__.py
pyescrypt-0.1.0.data/purelib/pyescrypt/pyescrypt.py
pyescrypt-0.1.0.data/purelib/pyescrypt/yescrypt.bin
pyescrypt-0.1.0.dist-info/LICENSE
pyescrypt-0.1.0.dist-info/METADATA
pyescrypt-0.1.0.dist-info/WHEEL
pyescrypt-0.1.0.dist-info/top_level.txt
pyescrypt-0.1.0.dist-info/RECORD
