Metadata-Version: 2.1
Name: pyescrypt
Version: 0.1.0
Summary: Python bindings for yescrypt: memory-hard, NIST-compliant password hashing.
Home-page: https://https://github.com/0xcb/pyescrypt
Author: Colt Blackmore
Author-email: coltblackmore+pyescrypt@gmail.com
License: BSD
License-File: LICENSE
Requires-Dist: cffi >=1.0.0
